tidas_sdk/__init__.py
tidas_sdk/py.typed
tidas_sdk/core/__init__.py
tidas_sdk/core/base.py
tidas_sdk/core/factory.py
tidas_sdk/core/markdown.py
tidas_sdk/core/multilang.py
tidas_sdk/entities/__init__.py
tidas_sdk/entities/contact.py
tidas_sdk/entities/flow.py
tidas_sdk/entities/flow_property.py
tidas_sdk/entities/lcia_method.py
tidas_sdk/entities/life_cycle_model.py
tidas_sdk/entities/process.py
tidas_sdk/entities/source.py
tidas_sdk/entities/unit_group.py
tidas_sdk/entities/utils.py
tidas_sdk/generated/__init__.py
tidas_sdk/generated/tidas_contacts.py
tidas_sdk/generated/tidas_contacts_category.py
tidas_sdk/generated/tidas_data_types.py
tidas_sdk/generated/tidas_flowproperties.py
tidas_sdk/generated/tidas_flowproperties_category.py
tidas_sdk/generated/tidas_flows.py
tidas_sdk/generated/tidas_flows_elementary_category.py
tidas_sdk/generated/tidas_flows_product_category.py
tidas_sdk/generated/tidas_lciamethods.py
tidas_sdk/generated/tidas_lciamethods_category.py
tidas_sdk/generated/tidas_lifecyclemodels.py
tidas_sdk/generated/tidas_locations_category.py
tidas_sdk/generated/tidas_processes.py
tidas_sdk/generated/tidas_processes_category.py
tidas_sdk/generated/tidas_sources.py
tidas_sdk/generated/tidas_sources_category.py
tidas_sdk/generated/tidas_unitgroups.py
tidas_sdk/generated/tidas_unitgroups_category.py
tidas_sdk/schemas/__init__.py
tidas_sdk/schemas/tidas_contacts.json
tidas_sdk/schemas/tidas_contacts_category.json
tidas_sdk/schemas/tidas_data_types.json
tidas_sdk/schemas/tidas_flowproperties.json
tidas_sdk/schemas/tidas_flowproperties_category.json
tidas_sdk/schemas/tidas_flows.json
tidas_sdk/schemas/tidas_flows_elementary_category.json
tidas_sdk/schemas/tidas_flows_product_category.json
tidas_sdk/schemas/tidas_lciamethods.json
tidas_sdk/schemas/tidas_lciamethods_category.json
tidas_sdk/schemas/tidas_lifecyclemodels.json
tidas_sdk/schemas/tidas_locations_category.json
tidas_sdk/schemas/tidas_processes.json
tidas_sdk/schemas/tidas_processes_category.json
tidas_sdk-0.1.7.dist-info/licenses/LICENSE
tidas_sdk-0.1.7.dist-info/METADATA
tidas_sdk-0.1.7.dist-info/WHEEL
tidas_sdk-0.1.7.dist-info/top_level.txt
tidas_sdk-0.1.7.dist-info/RECORD
