Metadata-Version: 2.4
Name: tidas-sdk
Version: 0.1.7
Summary: Python SDK for TIDAS/ILCD Life Cycle Assessment data
Author: Tiangong LCA Team
License: MIT
Project-URL: Homepage, https://github.com/tiangong-lca/tidas-sdk
Project-URL: Repository, https://github.com/tiangong-lca/tidas-sdk
Keywords: tidas,ilcd,lca,life-cycle-assessment
Requires-Python: >=3.12
License-File: LICENSE
Requires-Dist: pydantic<3.0,>=2.0
Requires-Dist: loguru>=0.7.0
Requires-Dist: typing-extensions>=4.0.0; python_version < "3.10"
Requires-Dist: jsonschema>=4.19.0
Provides-Extra: dev
Requires-Dist: pytest>=8.0; extra == "dev"
Requires-Dist: pytest-cov>=5.0; extra == "dev"
Requires-Dist: mypy>=1.10; extra == "dev"
Requires-Dist: ruff>=0.6.0; extra == "dev"
Requires-Dist: black>=24.0; extra == "dev"
Requires-Dist: pydocstyle>=6.3; extra == "dev"
Requires-Dist: datamodel-code-generator>=0.27.0; extra == "dev"
Dynamic: license-file
